minha_biblioteca_math/__init__.py
minha_biblioteca_math/funcoes_matematicas.py
minha_biblioteca_math-0.1.0.dist-info/METADATA
minha_biblioteca_math-0.1.0.dist-info/WHEEL
minha_biblioteca_math-0.1.0.dist-info/top_level.txt
minha_biblioteca_math-0.1.0.dist-info/RECORD
